sg_ag_libreria/__init__.py
sg_ag_libreria/funciones.py
sg_ag_libreria-0.1.0.dist-info/METADATA
sg_ag_libreria-0.1.0.dist-info/WHEEL
sg_ag_libreria-0.1.0.dist-info/top_level.txt
sg_ag_libreria-0.1.0.dist-info/RECORD
