Metadata-Version: 2.4
Name: sg_ag_libreria
Version: 0.1.0
Summary: Una libreria para algoritmos geneticos
Author: John Sebastian Galindo Hernandez
Author-email: johnsgalindo@ucundinamarca.edu.co
Classifier: Programming Language :: Python :: 3
Classifier: License :: OSI Approved :: MIT License
Classifier: Operating System :: OS Independent
Requires-Python: >=3.6
Dynamic: author
Dynamic: author-email
Dynamic: classifier
Dynamic: description
Dynamic: description-content-type
Dynamic: requires-python
Dynamic: summary
